README.md
setup.py
pysnip/__init__.py
pysnip/client.py
pysnip.egg-info/PKG-INFO
pysnip.egg-info/SOURCES.txt
pysnip.egg-info/dependency_links.txt
pysnip.egg-info/not-zip-safe
pysnip.egg-info/requires.txt
pysnip.egg-info/top_level.txt
pysnip/publish/__init__.py
pysnip/publish/__main__.py