Metadata-Version: 1.0
Name: pysnip
Version: 1.2.2
Summary: Python snippets
Home-page: https://github.com/AgeOfMarcus/pysnip
Author: AgeOfMarcus
Author-email: marcus@marcusweinberger.com
License: UNKNOWN
Platform: UNKNOWN
